something/__init__.py
something/interesting.py
conflict-0.1.1.dist-info/METADATA
conflict-0.1.1.dist-info/WHEEL
conflict-0.1.1.dist-info/top_level.txt
conflict-0.1.1.dist-info/RECORD
